py_fso/__init__.py
py_fso/folder.py
py_fso/textfile.py
py_fso-1.0.8.dist-info/LICENSE.md
py_fso-1.0.8.dist-info/METADATA
py_fso-1.0.8.dist-info/WHEEL
py_fso-1.0.8.dist-info/top_level.txt
py_fso-1.0.8.dist-info/RECORD
