Metadata-Version: 2.1
Name: py-fso
Version: 1.0.8
Summary: The Python package for working with dirs and files
Home-page: https://github.com/JustMisha/py_fso
Author: Mikhail Trusov
Author-email: admin@superprogrammist.ru
License: MIT
Classifier: Environment :: Console
Classifier: Intended Audience :: End Users/Desktop
Classifier: Intended Audience :: Developers
Classifier: Intended Audience :: System Administrators
Classifier: Operating System :: MacOS :: MacOS X
Classifier: Operating System :: Microsoft :: Windows
Classifier: Operating System :: POSIX
Classifier: Programming Language :: Python
Classifier: Topic :: System :: Filesystems
Classifier: Topic :: Utilities
License-File: LICENSE.md
